smalluuid/__init__.py
smalluuid/smalluuid.py
smalluuid/utils.py
tests/__init__.py
tests/test_smalluuid.py
tests/test_utils.py
smalluuid-1.1.0.dist-info/LICENSE.txt
smalluuid-1.1.0.dist-info/METADATA
smalluuid-1.1.0.dist-info/WHEEL
smalluuid-1.1.0.dist-info/top_level.txt
smalluuid-1.1.0.dist-info/RECORD
