Metadata-Version: 2.1
Name: smalluuid
Version: 1.1.0
Summary: Provides ShortUUID which extends Python's builtin UUID class
Home-page: https://github.com/adamcharnock/smalluuid
Author: Adam Charnock
Author-email: adam@adamcharnock.com
License: BSD
Platform: UNKNOWN
